LICENSE
MANIFEST.in
README.md
setup.py
conformance_tests/README
conformance_tests/custom/basic.json
conformance_tests/custom/basic_contains.output
conformance_tests/custom/basic_contains.selector
conformance_tests/custom/basic_empty.output
conformance_tests/custom/basic_empty.selector
conformance_tests/custom/basic_nth-last-child.output
conformance_tests/custom/basic_nth-last-child.selector
conformance_tests/upstream/.git
conformance_tests/upstream/.gitignore
conformance_tests/upstream/README.md
conformance_tests/upstream/level_1/basic.json
conformance_tests/upstream/level_1/basic_first-child.output
conformance_tests/upstream/level_1/basic_first-child.selector
conformance_tests/upstream/level_1/basic_grouping.output
conformance_tests/upstream/level_1/basic_grouping.selector
conformance_tests/upstream/level_1/basic_id.output
conformance_tests/upstream/level_1/basic_id.selector
conformance_tests/upstream/level_1/basic_id_multiple.output
conformance_tests/upstream/level_1/basic_id_multiple.selector
conformance_tests/upstream/level_1/basic_id_quotes.output
conformance_tests/upstream/level_1/basic_id_quotes.selector
conformance_tests/upstream/level_1/basic_id_with_type.output
conformance_tests/upstream/level_1/basic_id_with_type.selector
conformance_tests/upstream/level_1/basic_last-child.output
conformance_tests/upstream/level_1/basic_last-child.selector
conformance_tests/upstream/level_1/basic_nth-child-2.output
conformance_tests/upstream/level_1/basic_nth-child-2.selector
conformance_tests/upstream/level_1/basic_nth-child.output
conformance_tests/upstream/level_1/basic_nth-child.selector
conformance_tests/upstream/level_1/basic_nth-last-child.output
conformance_tests/upstream/level_1/basic_nth-last-child.selector
conformance_tests/upstream/level_1/basic_root_pseudo.output
conformance_tests/upstream/level_1/basic_root_pseudo.selector
conformance_tests/upstream/level_1/basic_type.output
conformance_tests/upstream/level_1/basic_type.selector
jsonselect.egg-info/PKG-INFO
jsonselect.egg-info/SOURCES.txt
jsonselect.egg-info/dependency_links.txt
jsonselect.egg-info/top_level.txt
