Metadata-Version: 1.0
Name: jsonselect
Version: 0.2.3
Summary: Python implementation of jsonselect (http://jsonselect.org/)
Home-page: https://github.com/mwhooker/jsonselect
Author: Matthew Hooker
Author-email: mwhooker@gmail.com
License: ISC
Keywords: json
Platform: UNKNOWN
Classifier: Development Status :: 2 - Pre-Alpha
Classifier: Intended Audience :: Developers
Classifier: Natural Language :: English
Classifier: License :: OSI Approved :: ISC License (ISCL)
Classifier: Programming Language :: Python
Classifier: Programming Language :: Python :: 2.6
Classifier: Programming Language :: Python :: 2.7
